dispatches_data/api/__init__.py
dispatches_data/api/_cli.py
dispatches_data/packages/_for_api_testing/README.md
dispatches_data/packages/_for_api_testing/__init__.py
dispatches_data/packages/_for_api_testing/data.jsonl
dispatches_data/testing/__init__.py
dispatches_data/testing/plugins.py
dispatches_data_packages-23.3.19.dist-info/LICENSE.md
dispatches_data_packages-23.3.19.dist-info/METADATA
dispatches_data_packages-23.3.19.dist-info/WHEEL
dispatches_data_packages-23.3.19.dist-info/entry_points.txt
dispatches_data_packages-23.3.19.dist-info/top_level.txt
dispatches_data_packages-23.3.19.dist-info/RECORD
