Metadata-Version: 2.1
Name: dispatches-data-packages
Version: 23.3.19
Requires-Python: >=3.8
License-File: LICENSE.md
Requires-Dist: importlib-metadata ; python_version < "3.10"
